py_casim/__init__.py
py_casim/casim.py
py_casim/cli.py
py_casim/tools.py
py_casim-2.0.3.dist-info/AUTHORS.rst
py_casim-2.0.3.dist-info/LICENSE
py_casim-2.0.3.dist-info/METADATA
py_casim-2.0.3.dist-info/WHEEL
py_casim-2.0.3.dist-info/entry_points.txt
py_casim-2.0.3.dist-info/top_level.txt
py_casim-2.0.3.dist-info/RECORD
