Metadata-Version: 2.1
Name: py-casim
Version: 2.0.3
Summary: Upload image
Home-page: https://github.com/Sergeileduc/py-casim
Author: Sergeileduc
Author-email: sergei.leduc@gmail.com
License: MIT license
Project-URL: Documentation, https://py-casim.readthedocs.io/en/latest/
Project-URL: Changelog, https://py-casim.readthedocs.io/en/latest/history.html
Project-URL: Source code, https://github.com/Sergeileduc/py-casim
Project-URL: Issue tracker, https://github.com/Sergeileduc/py-casim/issues
Project-URL: CI, https://travis-ci.org/github/Sergeileduc/py-casim
Keywords: python casim
Classifier: Development Status :: 5 - Production/Stable
Classifier: Intended Audience :: Developers
Classifier: License :: OSI Approved :: MIT License
Classifier: Natural Language :: English
Classifier: Programming Language :: Python :: 3
Classifier: Programming Language :: Python :: 3.6
Classifier: Programming Language :: Python :: 3.7
Classifier: Programming Language :: Python :: 3.8
Classifier: Programming Language :: Python :: 3.9
Requires-Python: >=3.6
License-File: LICENSE
License-File: AUTHORS.rst
Requires-Dist: click
Requires-Dist: click-help-colors
Requires-Dist: bs4
Requires-Dist: requests
